{
  "source": "commit_kb",
  "url": "https://commit.takshashila.org.in/decisions/2026-05-12-may-12-sesame-meeting-defence-fellows-fundraising-strategic.html",
  "title": "May 12 Sesame Meeting: Defence Fellows, Fundraising & Strategic Decisions – Commit — Takshashila Knowledge Base",
  "category": "decisions",
  "text": "May 12 Sesame Meeting: Defence Fellows, Fundraising & Strategic Decisions\ndecisions\nKey organizational decisions made on defence fellowship expansion, new fundraising strategies, and operational initiatives.\nPublished\nMay 12, 2026\nTL;DR\n: Key organizational decisions made on defence fellowship expansion, new fundraising strategies, and operational initiatives.\nKey Points\nDefence Fellows program to expand up to 6 positions with WASP-style workshop training and rigorous selection process\nNew fundraising approach targeting Ascend-type groups with ₹60K/year recurring donations offering 80G benefits and recognition\nAlumni campaign being developed for small recurring donations to diversify funding base\nStrategic partnerships being explored through AI hackathon collaboration and UnboxingBLR pitching opportunities\nDecisions Made\n✅ Aditya Ramanathan to conduct WASP-style workshop for Takshashila defence fellows\n✅ Defence Fellows program approved for up to 6 positions with rigorous selection criteria\n✅ Manoj to pitch recurring donation model (₹60K/year with 80G benefits) to Ascend-type donor groups\n✅ Manoj approved to conduct China study tour\nAction Items\nAditya Ramanathan to organize WASP-style workshop for defence fellows\nSowmya to discuss AI hackathon collaboration with Amita Prasanth Prakash\nManoj to pitch annual recurring donation program to Ascend-type groups\nPranay Kotas to develop alumni recurring donation campaign strategy\nCarl to share final NAX2.0 status update\nCarl to explore UnboxingBLR partnership opportunities for Takshashila\nSowmya to invite Awais to next physical board meeting\nManoj to organize China study tour\nContext\nThis appears to be a decision summary from a Sesame meeting (likely a regular leadership/strategy meeting at Takshashila). The decisions span operational expansion of the defence fellowship program, new fundraising strategies targeting high-value recurring donors, and various partnership and outreach initiatives to strengthen the organization's reach and financial sustainability.\nOriginal Thread\n[2026-05-12 05:12 UTC] @pranaykotas: Decisions on May 12 Sesame.\n\n1. @adityaramanathan to do WASP style workshop for Takshashila defence fellows.\n2. @adityaramanathan - it's okay to have up to 6 Defence Fellows but have rigorous selection. \n3. @sowmya to talk to Amita Prasanth Prakash related to Ashish's hackathon on AI idea.\n4. @manoj pitch to Ascend type of group - give an annual recurring donation with 80G. Like ₹60K/year. You can define a question but we will put it in the public domain. Pitch is about India's national interest. We will recognise you for events, podcasts, names on website. \n5. @pranaykotas to think about campaign for alumni to do recurring small donations\n6. @carl to share te latest final status of NAX2.0\n7. @carl to ask where UnboxingBLR can pitch Takshashila's work\n8. @sowmya to invite Awais for the next physical board meeting\n9. @manoj do China study tour\n\n[2026-05-12 05:12 UTC] @pranaykotas: !kb\n\n[2026-05-12 05:12 UTC] @kb-bot: Processing this thread...\nFrom #sesame · 2 participants · What We Decided",
  "text_length": 3093
}